[
{
 
  "petImage": "https://res.cloudinary.com/doocqhmpu/image/upload/v1700939696/x3ja5gvhzc3hphp67fqh.jpg",
  "petName": "pet",
  "petAge": 12,
  "category": "fish",
  "location": "chittagong",
  "short_description": "short description",
  "long_description": "long description",
  "addedDate": "2023-11-25T19:14:56.095Z",
  "adopted": true,
  "email": "sakibkahadi0@gmail.com"
  },
  {
  
  "petImage": "https://res.cloudinary.com/doocqhmpu/image/upload/v1700939872/nn3nwkklzig0hpxugtch.jpg",
  "petName": "pet",
  "petAge": 12,
  "category": "fish",
  "location": "chittagong",
  "short_description": "short description",
  "long_description": "long description",
  "addedDate": "2023-11-25T19:17:52.280Z",
  "adopted": true,
  "email": "sakibkahadi0@gmail.com"
  },
  {
  
  "petImage": "https://res.cloudinary.com/doocqhmpu/image/upload/v1700940050/miqlfiyudlneymndm9zz.jpg",
  "petName": "dog",
  "petAge": 2,
  "category": "fish",
  "location": "chittagong",
  "short_description": "short description",
  "long_description": "fffffffffffffff",
  "addedDate": "2023-11-25T19:20:50.253Z",
  "adopted": false,
  "email": "sakibkahadi72844@gmail.com"
  },
  {
  
  "petImage": "https://res.cloudinary.com/doocqhmpu/image/upload/v1700993826/xjhvdqrer4kfjurmmoxr.jpg",
  "petName": "fffffffffffffffff",
  "petAge": 11,
  "category": "rabbits",
  "location": "khulna",
  "short_description": "fffffffffffffffff",
  "long_description": "ffffffffff",
  "addedDate": "2023-11-26T10:17:02.283Z",
  "adopted": false,
  "email": "sakibkahadi0@gmail.com"
  },
  {
  
  "petImage": "https://res.cloudinary.com/doocqhmpu/image/upload/v1700993917/wtj0jqrk7caxasdjqbkd.jpg",
  "petName": "fff",
  "petAge": 2,
  "category": "fish",
  "location": "rajshahi",
  "short_description": "333",
  "long_description": "ffff",
  "addedDate": "2023-11-26T10:18:35.180Z",
  "adopted": false,
  "email": "sakibkahadi0@gmail.com"
  },
  {
  
  "petImage": "https://res.cloudinary.com/doocqhmpu/image/upload/v1700993985/ot84kk1bdup5hpixxntr.jpg",
  "petName": "pet",
  "petAge": 2,
  "category": "fish",
  "location": "chittagong",
  "short_description": "fffffffffffffffff",
  "long_description": "eeeeeeeeee",
  "addedDate": "2023-11-26T10:19:43.434Z",
  "adopted": false,
  "email": "sakibkahadi0@gmail.com"
  },
  {
  
  "petImage": "https://res.cloudinary.com/doocqhmpu/image/upload/v1701016193/j4tagmynnqfmqc2kheay.jpg",
  "petName": "sakib",
  "petAge": 123,
  "category": "rabbits",
  "location": "chittagong",
  "short_description": "short description",
  "long_description": "fff",
  "addedDate": "2023-11-26T16:29:49.107Z",
  "adopted": false,
  "email": "sakibkahadi0@gmail.com"
  },
  {
  
  "petImage": "https://res.cloudinary.com/doocqhmpu/image/upload/v1701016279/tiv8k6zhcmjoe3phzyc7.jpg",
  "petName": "kahadi",
  "petAge": 2,
  "category": "fish",
  "location": "khulna",
  "short_description": "short description",
  "long_description": "f",
  "addedDate": "2023-11-26T16:31:17.515Z",
  "adopted": false,
  "email": "sakibkahadi0@gmail.com"
  },
  {
  
  "petImage": "https://res.cloudinary.com/doocqhmpu/image/upload/v1701028495/nmq807xuoyejacpavmlq.jpg",
  "petName": "jamil",
  "petAge": 2,
  "category": "cats",
  "location": "rangpur",
  "short_description": "3333",
  "long_description": "ffff",
  "addedDate": "2023-11-26T19:54:52.495Z",
  "adopted": false,
  "email": "sakibkahadi0@gmail.com"
  }]